omron_2jcie_bu01/__init__.py
omron_2jcie_bu01/ble.py
omron_2jcie_bu01/serial.py
omron_2jcie_bu01_interact/__init__.py
omron_2jcie_bu01_interact/ble.py
omron_2jcie_bu01_interact/serial.py
omron_2jcie_bu01_interact-0.1.1.data/scripts/__init__.py
omron_2jcie_bu01_interact-0.1.1.data/scripts/ble.py
omron_2jcie_bu01_interact-0.1.1.data/scripts/serial.py
omron_2jcie_bu01_interact-0.1.1.dist-info/LICENSE
omron_2jcie_bu01_interact-0.1.1.dist-info/METADATA
omron_2jcie_bu01_interact-0.1.1.dist-info/WHEEL
omron_2jcie_bu01_interact-0.1.1.dist-info/top_level.txt
omron_2jcie_bu01_interact-0.1.1.dist-info/RECORD
