Metadata-Version: 2.1
Name: omron-2jcie-bu01-interact
Version: 0.1.1
Summary: API for OMRON 2JCIE-BU01 Environment Sensor
Home-page: https://github.com/andreastande/omron-2jcie-bu01-interact
Author: Andreas Tande
Author-email: andreas.tande@gmail.com
License: MIT
Platform: any
Classifier: Development Status :: 3 - Alpha
Classifier: Intended Audience :: Developers
Classifier: License :: OSI Approved :: MIT License
Classifier: Topic :: Home Automation
Classifier: Topic :: System :: Hardware
Classifier: Programming Language :: Python :: 3.6
Classifier: Programming Language :: Python :: 3.7
Classifier: Programming Language :: Python :: 3.8
License-File: LICENSE
Requires-Dist: pyserial
Provides-Extra: ble
Requires-Dist: bleak ; extra == 'ble'
